umitemplatedb/__init__.py
umitemplatedb/core.py
umitemplatedb/mongodb_schema.py
umitemplatedb-0.0.1.dist-info/LICENSE
umitemplatedb-0.0.1.dist-info/METADATA
umitemplatedb-0.0.1.dist-info/WHEEL
umitemplatedb-0.0.1.dist-info/top_level.txt
umitemplatedb-0.0.1.dist-info/RECORD
