Metadata-Version: 2.1
Name: umitemplatedb
Version: 0.0.1
Summary: Building Energy pandas extension
Home-page: https://github.com/MITSustainableDesignLab/umitemplatedb
Author: Samuel Letellier-Duchesne
Author-email: samueld@mit.edu
License: MIT
Keywords: archetypal umitemplatelibrary mongo mongoengine
Platform: UNKNOWN
Classifier: Development Status :: 4 - Beta
Classifier: Intended Audience :: Science/Research
Classifier: License :: OSI Approved :: MIT License
Classifier: Programming Language :: Python :: 3.7
Classifier: Programming Language :: Python :: 3.8
Classifier: Operating System :: OS Independent
Requires-Dist: archetypal (==2.1.3)
Requires-Dist: mongoengine (~=0.23.1)
Requires-Dist: pycountry (~=20.7.3)
Requires-Dist: pytest (~=6.2.4)
Requires-Dist: geojson (~=2.5.0)
Requires-Dist: mongomock (~=3.22.1)
Requires-Dist: datapackage (~=1.15.2)
